odoo/addons/l10n_ro_siruta/README.rst
odoo/addons/l10n_ro_siruta/__init__.py
odoo/addons/l10n_ro_siruta/__manifest__.py
odoo/addons/l10n_ro_siruta/hooks.py
odoo/addons/l10n_ro_siruta/demo/demo_siruta.xml
odoo/addons/l10n_ro_siruta/i18n/l10n_ro_siruta.pot
odoo/addons/l10n_ro_siruta/i18n/ro.po
odoo/addons/l10n_ro_siruta/models/__init__.py
odoo/addons/l10n_ro_siruta/models/res_partner.py
odoo/addons/l10n_ro_siruta/models/siruta.py
odoo/addons/l10n_ro_siruta/security/ir.model.access.csv
odoo/addons/l10n_ro_siruta/static/description/address.png
odoo/addons/l10n_ro_siruta/static/description/customer.png
odoo/addons/l10n_ro_siruta/static/description/icon.png
odoo/addons/l10n_ro_siruta/tests/__init__.py
odoo/addons/l10n_ro_siruta/tests/test_siruta.py
odoo/addons/l10n_ro_siruta/views/partner_view.xml
odoo/addons/l10n_ro_siruta/views/siruta_view.xml
odoo11_addon_l10n_ro_siruta-11.0.1.0.0.99.dev5.dist-info/METADATA
odoo11_addon_l10n_ro_siruta-11.0.1.0.0.99.dev5.dist-info/WHEEL
odoo11_addon_l10n_ro_siruta-11.0.1.0.0.99.dev5.dist-info/top_level.txt
odoo11_addon_l10n_ro_siruta-11.0.1.0.0.99.dev5.dist-info/RECORD
